visionfeed/__init__.py
visionfeed-0.1.0.dist-info/METADATA
visionfeed-0.1.0.dist-info/WHEEL
visionfeed-0.1.0.dist-info/RECORD
