Metadata-Version: 2.4
Name: visionfeed
Version: 0.1.0
Summary: VisionFeed by Intel Open Edge Platform
Author-email: Intel Open Edge Platform <open-edge-platform@intel.com>
License-Expression: Apache-2.0
Classifier: Development Status :: 3 - Alpha
Classifier: Intended Audience :: Developers
Classifier: License :: OSI Approved :: Apache Software License
Classifier: Operating System :: OS Independent
Classifier: Programming Language :: Python :: 3
Classifier: Topic :: Scientific/Engineering :: Artificial Intelligence
Classifier: Topic :: Scientific/Engineering :: Image Recognition
Requires-Python: >=3.8
